openpack_toolkit/__init__.py
openpack_toolkit/activity/__init__.py
openpack_toolkit/bin/__init__.py
openpack_toolkit/bin/file.py
openpack_toolkit/codalab/__init__.py
openpack_toolkit/codalab/operation_segmentation/__init__.py
openpack_toolkit/codalab/operation_segmentation/eval.py
openpack_toolkit/codalab/operation_segmentation/utils.py
openpack_toolkit/configs/__init__.py
openpack_toolkit/configs/_schema.py
openpack_toolkit/configs/datasets/__init__.py
openpack_toolkit/configs/datasets/annotations.py
openpack_toolkit/configs/datasets/splits.py
openpack_toolkit/configs/datasets/streams.py
openpack_toolkit/configs/releases.py
openpack_toolkit/configs/users.py
openpack_toolkit/data/__init__.py
openpack_toolkit/data/dataloader.py
openpack_toolkit/utils/__init__.py
openpack_toolkit/utils/io.py
openpack_toolkit/utils/notebook.py
openpack_toolkit/validation/__init__.py
openpack_toolkit/validation/file.py
openpack_toolkit-1.1.0.dist-info/entry_points.txt
openpack_toolkit-1.1.0.dist-info/WHEEL
openpack_toolkit-1.1.0.dist-info/METADATA
openpack_toolkit-1.1.0.dist-info/RECORD
