Metadata-Version: 2.1
Name: openpack-toolkit
Version: 1.1.0
Summary: Toolkit for OpenPack Dataset
Home-page: https://open-pack.github.io
License: MIT
Author: Yoshimura Naoya
Requires-Python: >=3.8,<4.0
Classifier: License :: OSI Approved :: MIT License
Classifier: Programming Language :: Python :: 3
Classifier: Programming Language :: Python :: 3.10
Classifier: Programming Language :: Python :: 3.8
Classifier: Programming Language :: Python :: 3.9
Requires-Dist: numpy (>=1.22.3,<2.0.0)
Requires-Dist: omegaconf (>=2.2.2,<3.0.0)
Requires-Dist: pandas (>=1.5.2,<2.0.0)
Requires-Dist: scikit-learn (>=1.2.0,<2.0.0)
Requires-Dist: scipy (>=1.7.3,<2.0.0)
Project-URL: Repository, https://github.com/open-pack/openpack-toolkit
